firebird/qa/__about__.py
firebird/qa/__init__.py
firebird/qa/fbtconv.py
firebird/qa/plugin.py
firebird_qa-0.20.2.dist-info/METADATA
firebird_qa-0.20.2.dist-info/WHEEL
firebird_qa-0.20.2.dist-info/entry_points.txt
firebird_qa-0.20.2.dist-info/licenses/LICENSE
firebird_qa-0.20.2.dist-info/RECORD
