Metadata-Version: 2.4
Name: firebird-qa
Version: 0.20.2
Summary: pytest plugin for Firebird QA
Project-URL: Home, https://github.com/FirebirdSQL/firebird-qa
Project-URL: Documentation, https://firebird-qa.rtfd.io
Project-URL: Issues, https://github.com/FirebirdSQL/firebird-qa/issues
Project-URL: Funding, https://github.com/sponsors/pcisar
Project-URL: Source, https://github.com/FirebirdSQL/firebird-qa
Author-email: Pavel Cisar <pcisar@users.sourceforge.net>
License: MIT License
License-File: LICENSE
Keywords: Collections,Configuration,Firebird,Hooks,Logging,Protobuf,Signals,Trace
Classifier: Development Status :: 5 - Production/Stable
Classifier: Framework :: Pytest
Classifier: Intended Audience :: Developers
Classifier: License :: OSI Approved :: MIT License
Classifier: Operating System :: MacOS
Classifier: Operating System :: Microsoft :: Windows
Classifier: Operating System :: POSIX :: Linux
Classifier: Programming Language :: Python :: 3 :: Only
Classifier: Programming Language :: Python :: 3.8
Classifier: Programming Language :: Python :: 3.9
Classifier: Programming Language :: Python :: 3.10
Classifier: Programming Language :: Python :: 3.11
Classifier: Programming Language :: Python :: 3.12
Classifier: Topic :: Database :: Database Engines/Servers
Classifier: Topic :: Software Development :: Testing
Requires-Python: <4,>=3.8
Requires-Dist: firebird-base~=1.8
Requires-Dist: firebird-driver~=1.10
Requires-Dist: psutil~=5.9
Requires-Dist: pytest>=7.4
